[{"url":"http://schedule.sxsw.com/2013/events/event_MS23318","start":"2013-03-14T06:00:00Z","ages":"18+","end":"2013-03-14T06:50:00Z","artist":"Flunk","day":"2013-03-13","hashTags":[],"venue":"18th Floor at Hilton Garden Inn"},{"name":"Flunk","url":"http://flunkmusic.com","genre":"Electronic","origin":"Oslo, NORWAY","videoURL":null,"imgURL":"http://img.sxsw.com/2013/bands/1074.jpg","songURL":"http://audio.sxsw.com/2013/mp3_by_artist_id/1074.mp3"},{"address":"500 N IH 35","name":"18th Floor at Hilton Garden Inn"}]