[{"url":"http://schedule.sxsw.com/2013/events/event_MS21425","start":"2013-03-13T02:00:00Z","ages":"21+","end":"2013-03-13T02:40:00Z","artist":"Lisa LeBlanc","day":"2013-03-12","hashTags":[],"venue":"Swan Dive"},{"name":"Lisa LeBlanc","url":"http://lisaleblanc.ca","genre":"Folk","origin":"Rosaireville, NB, CANADA","videoURL":"http://player.vimeo.com/video/58114692","imgURL":"http://img.sxsw.com/2013/bands/1154.jpg","songURL":"http://audio.sxsw.com/2013/mp3_by_artist_id/1154.mp3"},{"address":"615 Red River St","name":"Swan Dive"}]