[{"url":"http://schedule.sxsw.com/2013/events/event_MS23757","start":"2013-03-14T04:30:00Z","ages":"21+","end":"2013-03-14T05:00:00Z","artist":"Grape St.","day":"2013-03-13","hashTags":[],"venue":"Hotel Vegas Patio"},{"name":"Grape St.","url":"http://facebook.com/pages/Grape-St/188817311162794?ref=ts&fref=ts","genre":"Pop","origin":"Austin, TX","videoURL":null,"imgURL":"http://img.sxsw.com/2013/bands/3198.jpg","songURL":"http://audio.sxsw.com/2013/mp3_by_artist_id/3198.mp3"},{"address":"1500 E 6th St","name":"Hotel Vegas Patio"}]